har_capture/__init__.py
har_capture/__main__.py
har_capture/py.typed
har_capture/capture/__init__.py
har_capture/capture/browser.py
har_capture/capture/connectivity.py
har_capture/capture/deps.py
har_capture/capture/workflow.py
har_capture/cli/__init__.py
har_capture/cli/capture.py
har_capture/cli/main.py
har_capture/cli/sanitize.py
har_capture/cli/validate.py
har_capture/patterns/README.md
har_capture/patterns/__init__.py
har_capture/patterns/allowlist.json
har_capture/patterns/capture.json
har_capture/patterns/hasher.py
har_capture/patterns/loader.py
har_capture/patterns/pii.json
har_capture/patterns/sensitive.json
har_capture/sanitization/__init__.py
har_capture/sanitization/har.py
har_capture/sanitization/html.py
har_capture/validation/__init__.py
har_capture/validation/secrets.py
har_capture-0.2.4.dist-info/METADATA
har_capture-0.2.4.dist-info/WHEEL
har_capture-0.2.4.dist-info/entry_points.txt
har_capture-0.2.4.dist-info/licenses/LICENSE
har_capture-0.2.4.dist-info/RECORD
