Metadata-Version: 2.4
Name: har-capture
Version: 0.2.4
Summary: HAR capture and PII sanitization library for network traffic analysis
Project-URL: Homepage, https://github.com/solentlabs/har-capture
Project-URL: Documentation, https://github.com/solentlabs/har-capture#readme
Project-URL: Repository, https://github.com/solentlabs/har-capture
Project-URL: Issues, https://github.com/solentlabs/har-capture/issues
Project-URL: Changelog, https://github.com/solentlabs/har-capture/blob/main/CHANGELOG.md
Author-email: Solent Labs <dev@solentlabs.io>
License-Expression: MIT
License-File: LICENSE
Keywords: capture,har,http-archive,pii,playwright,sanitization
Classifier: Development Status :: 4 - Beta
Classifier: Intended Audience :: Developers
Classifier: License :: OSI Approved :: MIT License
Classifier: Operating System :: OS Independent
Classifier: Programming Language :: Python :: 3
Classifier: Programming Language :: Python :: 3.10
Classifier: Programming Language :: Python :: 3.11
Classifier: Programming Language :: Python :: 3.12
Classifier: Programming Language :: Python :: 3.13
Classifier: Topic :: Internet :: WWW/HTTP
Classifier: Topic :: Security
Classifier: Topic :: Software Development :: Libraries :: Python Modules
Classifier: Typing :: Typed
Requires-Python: >=3.10
Provides-Extra: capture
Requires-Dist: playwright>=1.40; extra == 'capture'
Provides-Extra: cli
Requires-Dist: typer>=0.12; extra == 'cli'
Provides-Extra: dev
Requires-Dist: hypothesis>=6.100; extra == 'dev'
Requires-Dist: mypy>=1.10; extra == 'dev'
Requires-Dist: pip-audit>=2.7; extra == 'dev'
Requires-Dist: pre-commit>=3.7; extra == 'dev'
Requires-Dist: pytest-cov>=4.0; extra == 'dev'
Requires-Dist: pytest-xdist>=3.5; extra == 'dev'
Requires-Dist: pytest>=8.0; extra == 'dev'
Requires-Dist: ruff>=0.5.0; extra == 'dev'
Provides-Extra: full
Requires-Dist: playwright>=1.40; extra == 'full'
Requires-Dist: typer>=0.12; extra == 'full'
